spurwing/Client.py
spurwing/__init__.py
spurwing/config.sample.py
spurwing/test_api.py
Spurwing-1.0.6.dist-info/LICENSE
Spurwing-1.0.6.dist-info/METADATA
Spurwing-1.0.6.dist-info/WHEEL
Spurwing-1.0.6.dist-info/top_level.txt
Spurwing-1.0.6.dist-info/RECORD
