Metadata-Version: 2.1
Name: Spurwing
Version: 1.0.6
Summary: Python Library for Spurwing API
Home-page: https://github.com/Spurwing/Spurwing-API-Python-Library/
Author: Ilya Nevolin
Author-email: ilya@spurwing.io
License: MIT License (MIT)
Platform: UNKNOWN
Requires-Dist: requests
